rss3/__init__.py
rss3/settings.py
rss3/interface/__init__.py
rss3/interface/items.py
rss3/interface/rss3.py
rss3/src/__init__.py
rss3/src/exceptions.py
rss3/src/file.py
rss3/src/index.py
rss3/src/item.py
rss3/src/items.py
rss3/src/link.py
rss3/src/links.py
rss3/src/persona.py
rss3/src/profile.py
rss3/utils/__init__.py
rss3/utils/account.py
rss3/utils/id.py
rss3-0.1.1.dist-info/LICENSE
rss3-0.1.1.dist-info/METADATA
rss3-0.1.1.dist-info/WHEEL
rss3-0.1.1.dist-info/top_level.txt
rss3-0.1.1.dist-info/RECORD
