Metadata-Version: 2.1
Name: rss3
Version: 0.1.1
Summary: Python library for RSS3
Home-page: https://github.com/LeetaoGoooo/RSS3-SDK-for-Python
Author: LeeTao
Author-email: leetao94cn@gmail.com
License: MIT
Keywords: rss3,rss
Platform: UNKNOWN
Classifier: License :: OSI Approved :: MIT License
Classifier: Programming Language :: Python
Classifier: Programming Language :: Python :: 3.7
Classifier: Programming Language :: Python :: 3.8
Classifier: Programming Language :: Python :: 3.9
License-File: LICENSE
Requires-Dist: aiohttp (>=3.7.4)
Requires-Dist: marshmallow-dataclass (>=8.4.1)
Requires-Dist: web3 (>=5.20.0)
